test_requires_python_3_warehouse/.__init__.py.un~
test_requires_python_3_warehouse/__init__.py
test_requires_python_3_warehouse-0.0.2.dist-info/WHEEL
test_requires_python_3_warehouse-0.0.2.dist-info/METADATA
test_requires_python_3_warehouse-0.0.2.dist-info/RECORD
